[
  {
    "ProductName": "TRAMADOL HYDROCHLORIDE",
    "Price": 516.48,
    "Seller": "JoshuaMurray"
  },
  {
    "ProductName": "Allopurinol",
    "Price": 518.50,
    "Seller": "PaulaHill"
  },
  {
    "ProductName": "Parsley",
    "Price": 519.06,
    "Seller": "FredBarnes"
  },
  {
    "ProductName": "equaline",
    "Price": 520.45,
    "Seller": "WandaHarris"
  },
  {
    "ProductName": "Extra Strength Pain Reliever PM",
    "Price": 542.72,
    "Seller": "CarlDaniels"
  },
  {
    "ProductName": "Propranolol Hydrochloride",
    "Price": 546.95,
    "Seller": "BettyLawson"
  },
  {
    "ProductName": "Prednisone",
    "Price": 550.72,
    "Seller": "ChristinaPatterson"
  },
  {
    "ProductName": "TERSI",
    "Price": 554.91
  },
  {
    "ProductName": "DAYWEAR PLUS MULTI PROTECTION TINTED MOISTURIZER",
    "Price": 555.12,
    "Seller": "BrendaHowell"
  },
  {
    "ProductName": "PLANTAGO LANCEOLATA POLLEN",
    "Price": 561.68,
    "Seller": "KathyGilbert"
  },
  {
    "ProductName": "Echinacea Quartz Gum Support",
    "Price": 570.08
  },
  {
    "ProductName": "Topiramate",
    "Price": 578.77
  },
  {
    "ProductName": "AIR",
    "Price": 581.69,
    "Seller": "GloriaAlexander"
  },
  {
    "ProductName": "Agaricus Equisetum Special Order",
    "Price": 585.93
  },
  {
    "ProductName": "Gemcitabine",
    "Price": 594.79,
    "Seller": "MarieWilliamson"
  },
  {
    "ProductName": "Ketorolac Tromethamine",
    "Price": 608.18,
    "Seller": "SandraRiley"
  },
  {
    "ProductName": "Pleo Ginkgo",
    "Price": 613.65,
    "Seller": "JoshuaMurray"
  },
  {
    "ProductName": "Diastat",
    "Price": 614.14,
    "Seller": "BonnieFox"
  },
  {
    "ProductName": "No7 Protect and Perfect Foundation Sunscreen Broad Spectrum SPF 15 Cool Ivory",
    "Price": 616.19,
    "Seller": "BrandonFuller"
  },
  {
    "ProductName": "Glipizide",
    "Price": 621.78,
    "Seller": "JeremyWoods"
  },
  {
    "ProductName": "AMARANTHUS PALMERI POLLEN",
    "Price": 623.16,
    "Seller": "ChristinaPatterson"
  },
  {
    "ProductName": "Foaming Hand Sanitizer",
    "Price": 624.72,
    "Seller": "BenjaminHenry"
  },
  {
    "ProductName": "ziprasidone hydrochloride",
    "Price": 628.66,
    "Seller": "ChristineGomez"
  },
  {
    "ProductName": "AVANDAMET",
    "Price": 632.08
  },
  {
    "ProductName": "Imipramine Hydrochloride",
    "Price": 648.69,
    "Seller": "ClarenceFowler"
  },
  {
    "ProductName": "Childrens Allegra Allergy",
    "Price": 650.97,
    "Seller": "DorisCook"
  },
  {
    "ProductName": "Strattera",
    "Price": 658.54
  },
  {
    "ProductName": "Amitiza",
    "Price": 666.58
  },
  {
    "ProductName": "ENBREL",
    "Price": 673.97,
    "Seller": "BrendaHowell"
  },
  {
    "ProductName": "Ampicillin",
    "Price": 674.63,
    "Seller": "AnnaClark"
  },
  {
    "ProductName": "PRIMAXIN",
    "Price": 686.66,
    "Seller": "FredAllen"
  },
  {
    "ProductName": "CLARINS Ever Matte SPF 15 - 105 Nude",
    "Price": 696.06,
    "Seller": "DorisCook"
  },
  {
    "ProductName": "CALMING DIAPER RASH",
    "Price": 700.92,
    "Seller": "EugeneStewart"
  },
  {
    "ProductName": "Acnezzol Base",
    "Price": 710.60
  },
  {
    "ProductName": "Prostate",
    "Price": 716.05,
    "Seller": "BrandonFuller"
  },
  {
    "ProductName": "Pleo Lat",
    "Price": 720.08,
    "Seller": "GloriaAlexander"
  },
  {
    "ProductName": "GOONG SECRET CALMING BATH",
    "Price": 742.47
  },
  {
    "ProductName": "Warfarin Sodium",
    "Price": 770.05,
    "Seller": "ChristinaPatterson"
  },
  {
    "ProductName": "Pollens - Weeds and Garden Plants, Nettle Urtica dioica",
    "Price": 782.77
  },
  {
    "ProductName": "Isosorbide Mononitrate",
    "Price": 789.91,
    "Seller": "ArthurReynolds"
  },
  {
    "ProductName": "Naproxen",
    "Price": 807.22,
    "Seller": "DorisCook"
  },
  {
    "ProductName": "Meloxicam",
    "Price": 809.18,
    "Seller": "WandaHarris"
  },
  {
    "ProductName": "Clarins Paris Skin Illusion - 114 cappuccino",
    "Price": 811.42
  },
  {
    "ProductName": "Azithromycin",
    "Price": 813.87,
    "Seller": "BonnieFox"
  },
  {
    "ProductName": "LV-FX",
    "Price": 820.87,
    "Seller": "FredAllen"
  },
  {
    "ProductName": "IOPE SUPER VITAL",
    "Price": 824.68,
    "Seller": "JacquelinePerez"
  },
  {
    "ProductName": "Aquafresh",
    "Price": 849.93,
    "Seller": "NicoleMartinez"
  },
  {
    "ProductName": "RESCRIPTOR",
    "Price": 850.52,
    "Seller": "ClarenceFowler"
  },
  {
    "ProductName": "Moore Medical Sinus Pain and Pressure Relief",
    "Price": 855.39,
    "Seller": "FredBarnes"
  },
  {
    "ProductName": "Shopko Lip Treatment",
    "Price": 861.42,
    "Seller": "BillyParker"
  },
  {
    "ProductName": "Perrigo Benzoyl Peroxide",
    "Price": 873.24,
    "Seller": "PatriciaCooper"
  },
  {
    "ProductName": "ESIKA",
    "Price": 879.37,
    "Seller": "JoshuaMurray"
  },
  {
    "ProductName": "Levothyroxine Sodium",
    "Price": 885.86,
    "Seller": "RachelJohnson"
  },
  {
    "ProductName": "EPZICOM",
    "Price": 895.65,
    "Seller": "FredBarnes"
  },
  {
    "ProductName": "Myristica Argentum Sinus Relief",
    "Price": 904.52,
    "Seller": "JoshuaMurray"
  },
  {
    "ProductName": "Aspirin",
    "Price": 925.45
  },
  {
    "ProductName": "Ranitidine",
    "Price": 926.64,
    "Seller": "ChristineGomez"
  },
  {
    "ProductName": "Care One Hemorrhoidal",
    "Price": 932.18
  },
  {
    "ProductName": "Spironolactone",
    "Price": 933.69
  },
  {
    "ProductName": "pain relief",
    "Price": 938.23,
    "Seller": "BrandonFuller"
  },
  {
    "ProductName": "Glipizide and Metformin Hydrochloride",
    "Price": 953.60,
    "Seller": "ThomasSnyder"
  },
  {
    "ProductName": "Metformin Hydrochloride",
    "Price": 953.99,
    "Seller": "ThomasSnyder"
  },
  {
    "ProductName": "Homeopathic Rheumatism",
    "Price": 967.08,
    "Seller": "AnnaParker"
  },
  {
    "ProductName": "NEO-POLY-BAC HYDRO",
    "Price": 967.32,
    "Seller": "JeremyWoods"
  },
  {
    "ProductName": "Clearskin",
    "Price": 968.59,
    "Seller": "ChristineGomez"
  },
  {
    "ProductName": "Dawn Ultra Antibacterial Hand",
    "Price": 969.86,
    "Seller": "DorisCook"
  },
  {
    "ProductName": "Megestrol Acetate",
    "Price": 976.15,
    "Seller": "PatrickKing"
  },
  {
    "ProductName": "Smooth texture Orange flavor",
    "Price": 976.65,
    "Seller": "BettyLawson"
  },
  {
    "ProductName": "Retin-A MICRO",
    "Price": 995.98,
    "Seller": "KathyGilbert"
  }
]